mg_alerts/__init__.py
mg_alerts/alert_models.py
mg_alerts/compile.py
mg_alerts/process_manager.py
mg_alerts/push_notifications/__init__.py
mg_alerts/signal/__init__.py
mg_alerts/telegram/__init__.py
mg_alerts/telegram/compile.py
mg_alerts/telegram/tg_alerts.py
mg_alerts/telegram/tg_base.py
mg_alerts/telegram/tg_config.py
mg_alerts/whatsapp/__init__.py
mg_alerts_ui5467-4.4.1.dist-info/METADATA
mg_alerts_ui5467-4.4.1.dist-info/WHEEL
mg_alerts_ui5467-4.4.1.dist-info/top_level.txt
mg_alerts_ui5467-4.4.1.dist-info/RECORD
