Metadata-Version: 2.4
Name: mg-alerts-ui5467
Version: 4.4.1
Author: Kenny
Requires-Python: >=3.10
Requires-Dist: mg-models-occ176
Requires-Dist: SQLAlchemy==1.*
Requires-Dist: Cython
Requires-Dist: keyrings.google.artifactregistry-auth
